sparsebit/__init__.py
sparsebit-0.0.1.dev0.dist-info/METADATA
sparsebit-0.0.1.dev0.dist-info/WHEEL
sparsebit-0.0.1.dev0.dist-info/top_level.txt
sparsebit-0.0.1.dev0.dist-info/RECORD
