Metadata-Version: 2.1
Name: sparsebit
Version: 0.0.1.dev0
Summary: sparsebit - model compression and acceleration
Author: Shadow Walker
License: UNKNOWN
Keywords: sparsebit
Platform: UNKNOWN
Classifier: Programming Language :: Python :: 3
Classifier: Programming Language :: Python :: 3.8
Classifier: Programming Language :: Python :: 3.9
Classifier: Programming Language :: Python :: 3.10
Requires-Dist: torch
